{
	"records": [
		{
			"name": "Met_inh",
			"records": [
				{
					"recid": 0,
					"id": "A",
					"V_Akt": "0",
					"D_Akt": "down",
					"D_ERK": "down",
					"D_MEK": "down",
					"V_ERK": "0",
					"V_MEK": "0"
				},
				{
					"recid": 1,
					"id": "B",
					"V_Akt": "0",
					"D_Akt": "down",
					"V_ERK": "0",
					"D_ERK": "down",
					"V_MEK": "0",
					"D_MEK": "down"
				},
				{
					"recid": 2,
					"id": "C",
					"V_Akt": "0",
					"D_Akt": "down",
					"V_ERK": "0",
					"D_ERK": "down",
					"V_MEK": "0",
					"D_MEK": "down"
				}
			],
			"recid": 0,
			"E_ERK": "",
			"E_Akt": "",
			"E_MEK": "",
			"E_Met": "0",
			"ending": "open",
			"select": true,
			"select_all": true,
			"E_HGF": "1"
		},
		{
			"name": "siRNA_ERK",
			"records": [
				{
					"recid": 0,
					"id": "A",
					"V_Akt": "",
					"D_Akt": "",
					"D_ERK": "down",
					"D_MEK": "",
					"V_ERK": "0"
				},
				{
					"recid": 1,
					"id": "B",
					"V_Akt": "",
					"D_Akt": "",
					"V_ERK": "0",
					"D_ERK": "down",
					"V_MEK": "1",
					"D_MEK": "up"
				},
				{
					"recid": 2,
					"id": "C",
					"V_Akt": "",
					"D_Akt": "",
					"V_ERK": "0",
					"D_ERK": "down",
					"V_MEK": "1",
					"D_MEK": "up"
				}
			],
			"recid": 4,
			"E_ERK": "0",
			"E_Akt": "",
			"E_MEK": "",
			"E_Met": "",
			"ending": "open",
			"select": true,
			"select_all": true,
			"E_Gab1": "",
			"E_HGF": "1"
		},
		{
			"name": "Mek_inh",
			"records": [
				{
					"recid": 0,
					"id": "A",
					"V_Akt": "",
					"D_Akt": "",
					"D_ERK": "down",
					"D_MEK": "down",
					"V_ERK": "0",
					"V_RSK": "0",
					"D_RSK": "down",
					"V_SOS1": "1",
					"D_SOS1": "up",
					"V_MEK": "1"
				},
				{
					"recid": 1,
					"id": "B",
					"V_Akt": "",
					"D_Akt": "",
					"V_ERK": "0",
					"D_ERK": "down",
					"V_MEK": "0",
					"D_MEK": "up",
					"V_RSK": "0",
					"D_RSK": "down",
					"V_SOS1": "1",
					"D_SOS1": "up"
				},
				{
					"recid": 2,
					"id": "C",
					"V_Akt": "",
					"D_Akt": "",
					"V_ERK": "0",
					"D_ERK": "down",
					"V_MEK": "1",
					"D_MEK": "up",
					"V_RSK": "0",
					"D_RSK": "down",
					"V_SOS1": "1",
					"D_SOS1": "up"
				}
			],
			"recid": 2,
			"E_ERK": "",
			"E_Akt": "",
			"E_MEK": "",
			"E_Met": "",
			"ending": "open",
			"select": true,
			"E_MEKIhn": "1",
			"select_all": true,
			"E_HGF": "1"
		},
		{
			"name": "PDK1_inh",
			"records": [
				{
					"recid": 0,
					"id": "A",
					"V_Akt": "0",
					"D_Akt": "down",
					"D_ERK": "down",
					"D_MEK": "down",
					"V_ERK": "1",
					"V_RSK": "0",
					"D_RSK": "down",
					"V_SOS1": "",
					"D_SOS1": "",
					"V_MEK": "1"
				},
				{
					"recid": 1,
					"id": "B",
					"V_Akt": "0",
					"D_Akt": "down",
					"V_ERK": "0",
					"D_ERK": "up",
					"V_MEK": "0",
					"D_MEK": "up",
					"V_RSK": "0",
					"D_RSK": "down",
					"V_SOS1": "",
					"D_SOS1": ""
				},
				{
					"recid": 2,
					"id": "C",
					"V_Akt": "0",
					"D_Akt": "down",
					"V_ERK": "1",
					"D_ERK": "up",
					"V_MEK": "1",
					"D_MEK": "up",
					"V_RSK": "0",
					"D_RSK": "down",
					"V_SOS1": "",
					"D_SOS1": ""
				}
			],
			"recid": 5,
			"E_ERK": "",
			"E_Akt": "",
			"E_MEK": "",
			"E_Met": "",
			"E_PDK1": "0",
			"ending": "open",
			"select": true,
			"E_MEKIhn": "",
			"select_all": true,
			"E_HGF": "1"
		},
		{
			"name": "Mek_and_PDK1_inh",
			"records": [
				{
					"recid": 0,
					"id": "A",
					"V_Akt": "0",
					"D_Akt": "down",
					"D_ERK": "down",
					"D_MEK": "down",
					"V_ERK": "0",
					"V_RSK": "0",
					"D_RSK": "down",
					"V_SOS1": "",
					"D_SOS1": "",
					"V_MEK": "1"
				},
				{
					"recid": 1,
					"id": "B",
					"V_Akt": "0",
					"D_Akt": "down",
					"V_ERK": "0",
					"D_ERK": "down",
					"V_MEK": "0",
					"D_MEK": "up",
					"V_RSK": "0",
					"D_RSK": "down",
					"V_SOS1": "",
					"D_SOS1": ""
				},
				{
					"recid": 2,
					"id": "C",
					"V_Akt": "0",
					"D_Akt": "down",
					"V_ERK": "0",
					"D_ERK": "down",
					"V_MEK": "1",
					"D_MEK": "up",
					"V_RSK": "0",
					"D_RSK": "down",
					"V_SOS1": "",
					"D_SOS1": ""
				}
			],
			"recid": 3,
			"E_ERK": "",
			"E_Akt": "",
			"E_MEK": "",
			"E_Met": "",
			"E_PDK1": "0",
			"ending": "open",
			"select": true,
			"E_MEKIhn": "1",
			"select_all": true,
			"E_HGF": "1"
		}
	]
}